setup.py
dhanes_probability/Binomialdistribution.py
dhanes_probability/Gaussiandistribution.py
dhanes_probability/Generaldistribution.py
dhanes_probability/__init__.py
dhanes_probability.egg-info/PKG-INFO
dhanes_probability.egg-info/SOURCES.txt
dhanes_probability.egg-info/dependency_links.txt
dhanes_probability.egg-info/not-zip-safe
dhanes_probability.egg-info/top_level.txt