Metadata-Version: 1.0
Name: dhanes-probability
Version: 0.1
Summary: dhanes_probability
Home-page: UNKNOWN
Author: Dhaneswara Mandrasa
Author-email: UNKNOWN
License: UNKNOWN
Platform: UNKNOWN
